ytvs/__init__.py
ytvs/api.py
ytvs/client/__init__.py
ytvs/client/official/api.py
ytvs/client/official/resources/__init__.py
ytvs/client/official/resources/activities.py
ytvs/client/official/resources/base_resource.py
ytvs/client/official/resources/captions.py
ytvs/client/official/resources/channel_banners.py
ytvs/client/official/resources/channel_sections.py
ytvs/client/official/resources/channels.py
ytvs/client/official/resources/comment_threads.py
ytvs/client/official/resources/comments.py
ytvs/client/official/resources/i18n_languages.py
ytvs/client/official/resources/i18n_regions.py
ytvs/client/official/resources/members.py
ytvs/client/official/resources/membership_levels.py
ytvs/client/official/resources/playlist_items.py
ytvs/client/official/resources/playlists.py
ytvs/client/official/resources/search.py
ytvs/client/official/resources/subscriptions.py
ytvs/client/official/resources/thumbnails.py
ytvs/client/official/resources/video_abuse_report_reasons.py
ytvs/client/official/resources/video_categories.py
ytvs/client/official/resources/videos.py
ytvs/client/official/resources/watermarks.py
ytvs/client/unofficial/__init__.py
ytvs/client/unofficial/api.py
ytvs/client/unofficial/client.py
ytvs/client/unofficial/constants.py
ytvs/client/unofficial/parameter.py
ytvs/client/unofficial/resources/__init__.py
ytvs/client/unofficial/resources/base_resource.py
ytvs/client/unofficial/resources/channel.py
ytvs/client/unofficial/resources/comment_reply.py
ytvs/client/unofficial/resources/comment_thread.py
ytvs/client/unofficial/resources/search.py
ytvs/client/unofficial/resources/transcript.py
ytvs/client/unofficial/resources/video.py
ytvs/compatible.py
ytvs/constants.py
ytvs/embedding_iframe_api_creator.py
ytvs/embedding_permission_checker.py
ytvs/error.py
ytvs/exception.py
ytvs/extractor/__init__.py
ytvs/filter.py
ytvs/models/__init__.py
ytvs/models/activity.py
ytvs/models/auth.py
ytvs/models/base.py
ytvs/models/caption.py
ytvs/models/category.py
ytvs/models/channel.py
ytvs-0.0.28.dist-info/METADATA
ytvs-0.0.28.dist-info/WHEEL
ytvs-0.0.28.dist-info/RECORD
