Metadata-Version: 2.1
Name: ytvs
Version: 0.0.28
Summary: 
Author: HHH_HHH
Author-email: kukkuk989@protonmail.com
Requires-Python: >=3.8,<4.0
Classifier: Programming Language :: Python :: 3
Classifier: Programming Language :: Python :: 3.8
Classifier: Programming Language :: Python :: 3.9
Classifier: Programming Language :: Python :: 3.10
Classifier: Programming Language :: Python :: 3.11
Classifier: Programming Language :: Python :: 3.12
Requires-Dist: dataclasses-json (>=0.6.4,<0.7.0)
Requires-Dist: isodate (>=0.6.1,<0.7.0)
Requires-Dist: python-youtube (>=0.9.3,<0.10.0)
Requires-Dist: stem (>=1.8.2,<2.0.0)
